django_pulse/__init__.py
django_pulse/apps.py
django_pulse/consumers.py
django_pulse/init.py
django_pulse/models.py
django_pulse/routing.py
django_pulse/signals.py
django_pulse-1.0.1.dist-info/licenses/LICENSE
django_pulse-1.0.1.dist-info/METADATA
django_pulse-1.0.1.dist-info/WHEEL
django_pulse-1.0.1.dist-info/top_level.txt
django_pulse-1.0.1.dist-info/RECORD
