Metadata-Version: 2.4
Name: django-pulse
Version: 1.0.1
Summary: Backend sync engine for pulse-rn
Home-page: https://github.com/JesusM15/django-pulse
Author: Jesus M.
Classifier: Framework :: Django
Classifier: Programming Language :: Python :: 3
Classifier: License :: OSI Approved :: MIT License
Classifier: Operating System :: OS Independent
Requires-Python: >=3.7
License-File: LICENSE
Requires-Dist: django>=3.2
Requires-Dist: channels>=3.0
Requires-Dist: channels-redis>=3.0
Requires-Dist: asgiref>=3.3
Dynamic: author
Dynamic: classifier
Dynamic: description
Dynamic: description-content-type
Dynamic: home-page
Dynamic: license-file
Dynamic: requires-dist
Dynamic: requires-python
Dynamic: summary
